match_snapshot/__init__.py
match_snapshot/match_snapshot.py
tiny_match_snapshot-0.0.2.dist-info/LICENSE
tiny_match_snapshot-0.0.2.dist-info/METADATA
tiny_match_snapshot-0.0.2.dist-info/WHEEL
tiny_match_snapshot-0.0.2.dist-info/top_level.txt
tiny_match_snapshot-0.0.2.dist-info/RECORD
