Metadata-Version: 2.1
Name: tiny-match-snapshot
Version: 0.0.2
Summary: Tiny snapshot assertion for tests
Author-email: Eduardo Oliveira <eduardo_y05@outlook.com>
Maintainer-email: Eduardo Oliveira <eduardo_y05@outlook.com>
License: MIT License
Project-URL: homepage, https://github.com/inventare/tiny-match-snapshot/
Project-URL: documentation, https://github.com/inventare/tiny-match-snapshot/
Keywords: snapshot,test,image,match,assertion,playwright,selenium
Classifier: Development Status :: 5 - Production/Stable
Classifier: Environment :: Web Environment
Classifier: Intended Audience :: Developers
Classifier: License :: OSI Approved :: MIT License
Classifier: Operating System :: OS Independent
Classifier: Programming Language :: Python
Classifier: Programming Language :: Python :: 3
Classifier: Programming Language :: Python :: 3.8
Classifier: Programming Language :: Python :: 3.9
Classifier: Programming Language :: Python :: 3.10
Classifier: Programming Language :: Python :: 3.11
Classifier: Programming Language :: Python :: 3.12
Requires-Python: >=3.8
License-File: LICENSE
Requires-Dist: Pillow
Provides-Extra: dev
Requires-Dist: black ; extra == 'dev'
Requires-Dist: isort ; extra == 'dev'
Requires-Dist: pre-commit ; extra == 'dev'
Provides-Extra: tests
Requires-Dist: pytest ; extra == 'tests'
